django_quicky/__init__.py
django_quicky/context_processors.py
django_quicky/decorators.py
django_quicky/fields.py
django_quicky/forms.py
django_quicky/middleware.py
django_quicky/models.py
django_quicky/utils.py
django_quicky/deploy/__init__.py
django_quicky/management/__init__.py
django_quicky/management/commands/__init__.py
django_quicky/management/commands/clear_sessions.py
django_quicky/management/commands/generate_secret_key.py
django_quicky/management/commands/hard_reset_db.py
django_quicky/namegen/__init__.py
django_quicky/namegen/namegen.py
django_quicky/namegen/names.py
django_quicky/templates/django_quicky/no_cookies.html
django_quicky/templatetags/__init__.py
django_quicky/templatetags/introspection.py
django_quicky-0.7.3.dist-info/METADATA
django_quicky-0.7.3.dist-info/WHEEL
django_quicky-0.7.3.dist-info/top_level.txt
django_quicky-0.7.3.dist-info/RECORD
