Metadata-Version: 2.1
Name: django-quicky
Version: 0.7.3
Summary: A collection of tools to make setting up Django quicker.
Home-page: https://github.com/sametmax/django-quicky
Author: Sam et Max
Author-email: lesametlemax@gmail.com
License: UNKNOWN
Platform: UNKNOWN
Classifier: Programming Language :: Python
Classifier: Intended Audience :: Information Technology
Classifier: License :: OSI Approved :: zlib/libpng License
Classifier: Natural Language :: English
Classifier: Programming Language :: Python :: 2.7
Classifier: Programming Language :: Python :: 3.3
Requires-Dist: django
